baddeley_binary_image_metric/__init__.py
baddeley_binary_image_metric/locmeasures2d_default.py
baddeley_binary_image_metric/locmeasures2d_prep.py
baddeley_binary_image_metric/locmeasures2d_spatial_vx.py
baddeley_binary_image_metric/lib/__init__.py
baddeley_binary_image_metric/lib/as_unitname.py
baddeley_binary_image_metric/lib/datagrabber_spatialVx.py
baddeley_binary_image_metric/lib/deltametric.py
baddeley_binary_image_metric/lib/distmap.py
baddeley_binary_image_metric/lib/im.py
baddeley_binary_image_metric/lib/loc_list_setup.py
baddeley_binary_image_metric/lib/locperf.py
baddeley_binary_image_metric/lib/make_spatialVx.py
baddeley_binary_image_metric/lib/solutionset.py
fqi/__init__.py
fqi/fqi.py
fqi/uiqi.py
fqi/lib/__init__.py
fqi/lib/aaft2d.py
fqi/lib/ampstats.py
fqi/lib/cbind.py
fqi/lib/datagrabber_spatialVx.py
fqi/lib/distfun.py
fqi/lib/fft2d.py
fqi/lib/im.py
fqi/lib/locmeasures2d_prep.py
fqi/lib/locperf.py
fqi/lib/locperfer.py
fqi/lib/mae.py
fqi/lib/solutionset.py
fqi/lib/surrogater2d.py
fqi/lib/util.py
fqi/lib/zapsmall.py
meteva/__init__.py
meteva/setup.py
meteva/base/__init__.py
meteva/base/basicdata/__init__.py
meteva/base/basicdata/const.py
meteva/base/basicdata/ctl.py
meteva/base/basicdata/dicts.py
meteva/base/basicdata/grid.py
meteva/base/basicdata/grid_data.py
meteva/base/basicdata/keys.py
meteva/base/basicdata/sta_data.py
meteva/base/fun/__init__.py
meteva/base/fun/combining.py
meteva/base/fun/computing.py
meteva/base/fun/diagnosing.py
meteva/base/fun/grouping.py
meteva/base/fun/interpolating.py
meteva/base/fun/nearing.py
meteva/base/fun/selecting.py
meteva/base/fun/statisticing.py
meteva/base/fun/timing.py
meteva/base/fun/transformating.py
meteva/base/function/__init__.py
meteva/base/function/get_from_grid_data.py
meteva/base/function/get_from_sta_data.py
meteva/base/function/gxy_gxy.py
meteva/base/function/gxy_gxym.py
meteva/base/function/gxy_sxy.py
meteva/base/function/gxym_gxy.py
meteva/base/function/gxym_gxym.py
meteva-1.9.2.6.dist-info/METADATA
meteva-1.9.2.6.dist-info/WHEEL
meteva-1.9.2.6.dist-info/top_level.txt
meteva-1.9.2.6.dist-info/RECORD
