Metadata-Version: 2.1
Name: meteva
Version: 1.9.2.6
Summary: A collections of functions for meteorological verification.
Author: liucouhua,daikan,wangbaoli,tangbuxing
Author-email: liucouhua@163.com
License: GPL3
Classifier: Development Status :: 3 - Alpha
Classifier: Intended Audience :: Developers
Classifier: Programming Language :: Python :: 3
Requires-Dist: numpy >=1.12.1
Requires-Dist: pandas >=1.0.4
Requires-Dist: netCDF4 >=1.4.1
Requires-Dist: scipy >=0.19.0
Requires-Dist: xarray >=0.10.0
Requires-Dist: scikit-learn >=0.21.2
Requires-Dist: matplotlib >=3.2.2
Requires-Dist: httplib2 >=0.12.0
Requires-Dist: protobuf >=1.0.0
Requires-Dist: pyshp >=2.1.0
Requires-Dist: tables >=3.4.4
Requires-Dist: urllib3 >=1.21.1
Requires-Dist: pynverse >=0.1.4.6
Requires-Dist: shapely >=1.8.0
Requires-Dist: importlib-resources >=5.2.1
